{"nodes": [{"id": "users_shivansh_desktop_hackathon_clearpass_scripts_run_demo_sh", "label": "run-demo.sh", "file_type": "code", "source_file": "scripts/run-demo.sh", "source_location": "L1", "metadata": {"language": "bash", "kind": "file"}}, {"id": "users_shivansh_desktop_hackathon_clearpass_scripts_run_demo_sh__entry", "label": "run-demo.sh script", "file_type": "code", "source_file": "scripts/run-demo.sh", "source_location": "L1", "metadata": {"language": "bash", "kind": "bash_entrypoint"}}, {"id": "scripts_run_demo_path", "label": "PATH", "file_type": "code", "source_file": "scripts/run-demo.sh", "source_location": "L5", "metadata": {"language": "bash", "kind": "code"}}, {"id": "scripts_run_demo_verify_circuit", "label": "verify_circuit()", "file_type": "code", "source_file": "scripts/run-demo.sh", "source_location": "L10", "metadata": {"language": "bash", "kind": "bash_function"}}], "edges": [{"source": "users_shivansh_desktop_hackathon_clearpass_scripts_run_demo_sh", "target": "users_shivansh_desktop_hackathon_clearpass_scripts_run_demo_sh__entry", "relation": "contains", "confidence": "EXTRACTED", "source_file": "scripts/run-demo.sh", "source_location": "L1", "weight": 1.0}, {"source": "users_shivansh_desktop_hackathon_clearpass_scripts_run_demo_sh", "target": "scripts_run_demo_path", "relation": "defines", "confidence": "EXTRACTED", "source_file": "scripts/run-demo.sh", "source_location": "L5", "weight": 1.0}, {"source": "users_shivansh_desktop_hackathon_clearpass_scripts_run_demo_sh", "target": "scripts_run_demo_verify_circuit", "relation": "defines", "confidence": "EXTRACTED", "source_file": "scripts/run-demo.sh", "source_location": "L10", "weight": 1.0}, {"source": "users_shivansh_desktop_hackathon_clearpass_scripts_run_demo_sh__entry", "target": "scripts_run_demo_verify_circuit", "relation": "calls", "confidence": "EXTRACTED", "source_file": "scripts/run-demo.sh", "source_location": "L25", "weight": 1.0, "context": "call"}]}